completions/__init__.py
completions/__init__.py.bak
completions/templates.py
completions-0.0.8.dist-info/entry_points.txt
completions-0.0.8.dist-info/WHEEL
completions-0.0.8.dist-info/METADATA
completions-0.0.8.dist-info/RECORD
