Metadata-Version: 2.1
Name: completions
Version: 0.0.8
Summary: Shell completions made easy.
Home-page: https://github.com/pwwang/completions
License: MIT
Author: pwwang
Author-email: pwwang@pwwang.com
Requires-Python: >=3.4,<4.0
Classifier: License :: OSI Approved :: MIT License
Classifier: Programming Language :: Python :: 3
Classifier: Programming Language :: Python :: 3.4
Classifier: Programming Language :: Python :: 3.5
Classifier: Programming Language :: Python :: 3.6
Classifier: Programming Language :: Python :: 3.7
Classifier: Programming Language :: Python :: 3.8
Requires-Dist: colorama
Requires-Dist: pyparam
Requires-Dist: python-simpleconf
Project-URL: Repository, https://github.com/pwwang/completions
